swarmauri_evaluator_externalimports/ExternalImportsEvaluator.py
swarmauri_evaluator_externalimports/__init__.py
swarmauri_evaluator_externalimports-0.1.2.dist-info/LICENSE
swarmauri_evaluator_externalimports-0.1.2.dist-info/METADATA
swarmauri_evaluator_externalimports-0.1.2.dist-info/WHEEL
swarmauri_evaluator_externalimports-0.1.2.dist-info/entry_points.txt
swarmauri_evaluator_externalimports-0.1.2.dist-info/RECORD
