Metadata-Version: 2.3
Name: swarmauri_evaluator_externalimports
Version: 0.1.2
Summary: Evaluator that detects and penalizes non-built-in Python imports in source files
License: Apache-2.0
Keywords: swarmauri,evaluator,imports,dependencies,static analysis,code quality,external modules,standard library
Author: SwarmAuri Team
Author-email: info@swarmauri.com
Requires-Python: >=3.10,<3.13
Classifier: License :: OSI Approved :: Apache Software License
Classifier: Natural Language :: English
Classifier: Programming Language :: Python :: 3.10
Classifier: Programming Language :: Python :: 3.11
Classifier: Programming Language :: Python :: 3.12
Classifier: Development Status :: 3 - Alpha
Requires-Dist: swarmauri_base
Requires-Dist: swarmauri_core
